trove_classifiers_cli/__init__.py
trove_classifiers_cli/cli.py
trove_classifiers_cli-0.2.2.dist-info/entry_points.txt
trove_classifiers_cli-0.2.2.dist-info/LICENSE
trove_classifiers_cli-0.2.2.dist-info/WHEEL
trove_classifiers_cli-0.2.2.dist-info/METADATA
trove_classifiers_cli-0.2.2.dist-info/RECORD
