Metadata-Version: 2.1
Name: trove-classifiers-cli
Version: 0.2.2
Summary: 
Home-page: https://github.com/tddschn/trove-classifiers-cli
License: MIT
Keywords: cli,trove-classifiers
Author: Xinyuan Chen
Author-email: 45612704+tddschn@users.noreply.github.com
Requires-Python: >=3.10,<4.0
Classifier: License :: OSI Approved :: MIT License
Classifier: Programming Language :: Python :: 3
Classifier: Programming Language :: Python :: 3.10
Classifier: Programming Language :: Python :: Implementation :: CPython
Classifier: Topic :: Utilities
Requires-Dist: trove-classifiers (>=2022.4.30,<2023.0.0)
Project-URL: Bug Tracker, https://github.com/tddschn/trove-classifiers-cli/issues
Project-URL: Repository, https://github.com/tddschn/trove-classifiers-cli
